{
  "$schema": "https://developer.microsoft.com/json-schemas/fabric/item/report/definition/visualContainer/2.7.0/schema.json",
  "name": "fe94fd4b9edaa058b75b",
  "position": {
    "x": 0,
    "y": 0,
    "z": 1000,
    "height": 72.857142857142861,
    "width": 1300,
    "tabOrder": 0
  },
  "visual": {
    "visualType": "columnChart",
    "query": {
      "queryState": {
        "Category": {
          "projections": [
            {
              "field": {
                "Column": {
                  "Expression": {
                    "SourceRef": {
                      "Entity": "CompanyMasters"
                    }
                  },
                  "Property": "Sub Company"
                }
              },
              "queryRef": "CompanyMasters.Company",
              "nativeQueryRef": "Sub Company",
              "active": true
            }
          ]
        },
        "Y": {
          "projections": [
            {
              "field": {
                "Aggregation": {
                  "Expression": {
                    "Column": {
                      "Expression": {
                        "SourceRef": {
                          "Entity": "CompanyMasters"
                        }
                      },
                      "Property": "Legend"
                    }
                  },
                  "Function": 0
                }
              },
              "queryRef": "Sum(CompanyMasters.Legend)",
              "nativeQueryRef": "Sum of Legend"
            }
          ]
        }
      },
      "sortDefinition": {
        "sort": [
          {
            "field": {
              "Aggregation": {
                "Expression": {
                  "Column": {
                    "Expression": {
                      "SourceRef": {
                        "Entity": "CompanyMasters"
                      }
                    },
                    "Property": "Legend"
                  }
                },
                "Function": 0
              }
            },
            "direction": "Descending"
          }
        ],
        "isDefaultSort": true
      }
    },
    "objects": {
      "categoryAxis": [
        {
          "properties": {
            "show": {
              "expr": {
                "Literal": {
                  "Value": "false"
                }
              }
            },
            "showAxisTitle": {
              "expr": {
                "Literal": {
                  "Value": "false"
                }
              }
            },
            "preferredCategoryWidth": {
              "expr": {
                "Literal": {
                  "Value": "20D"
                }
              }
            },
            "innerPadding": {
              "expr": {
                "Literal": {
                  "Value": "5L"
                }
              }
            }
          }
        }
      ],
      "valueAxis": [
        {
          "properties": {
            "show": {
              "expr": {
                "Literal": {
                  "Value": "false"
                }
              }
            },
            "showAxisTitle": {
              "expr": {
                "Literal": {
                  "Value": "false"
                }
              }
            },
            "invertAxis": {
              "expr": {
                "Literal": {
                  "Value": "false"
                }
              }
            },
            "start": {
              "expr": {
                "Literal": {
                  "Value": "-1D"
                }
              }
            },
            "end": {
              "expr": {
                "Literal": {
                  "Value": "1D"
                }
              }
            }
          }
        }
      ],
      "labels": [
        {
          "properties": {
            "show": {
              "expr": {
                "Literal": {
                  "Value": "true"
                }
              }
            },
            "enableValueDataLabel": {
              "expr": {
                "Literal": {
                  "Value": "false"
                }
              }
            },
            "enableDetailDataLabel": {
              "expr": {
                "Literal": {
                  "Value": "true"
                }
              }
            },
            "enableTitleDataLabel": {
              "expr": {
                "Literal": {
                  "Value": "false"
                }
              }
            },
            "detailFontSize": {
              "expr": {
                "Literal": {
                  "Value": "10D"
                }
              }
            },
            "detailFontFamily": {
              "expr": {
                "Literal": {
                  "Value": "'Calibri'"
                }
              }
            },
            "labelPosition": {
              "expr": {
                "Literal": {
                  "Value": "'InsideCenter'"
                }
              }
            },
            "detailBold": {
              "expr": {
                "Literal": {
                  "Value": "false"
                }
              }
            },
            "detailColor": {
              "solid": {
                "color": {
                  "expr": {
                    "ThemeDataColor": {
                      "ColorId": 1,
                      "Percent": 0
                    }
                  }
                }
              }
            }
          }
        },
        {
          "properties": {
            "dynamicLabelDetail": {
              "expr": {
                "Aggregation": {
                  "Expression": {
                    "Column": {
                      "Expression": {
                        "SourceRef": {
                          "Entity": "agg_revenue_call_report"
                        }
                      },
                      "Property": "Sub-Company"
                    }
                  },
                  "Function": 3
                }
              }
            }
          },
          "selector": {
            "data": [
              {
                "dataViewWildcard": {
                  "matchingOption": 1
                }
              }
            ],
            "highlightMatching": 1
          }
        }
      ],
      "dataPoint": [
        {
          "properties": {
            "borderShow": {
              "expr": {
                "Literal": {
                  "Value": "true"
                }
              }
            },
            "borderColorMatchFill": {
              "expr": {
                "Literal": {
                  "Value": "true"
                }
              }
            },
            "borderOutlineOnly": {
              "expr": {
                "Literal": {
                  "Value": "true"
                }
              }
            },
            "fillTransparency": {
              "expr": {
                "Literal": {
                  "Value": "0D"
                }
              }
            }
          }
        },
        {
          "properties": {
            "fill": {
              "solid": {
                "color": {
                  "expr": {
                    "Literal": {
                      "Value": "'#5F9EA0'"
                    }
                  }
                }
              }
            }
          },
          "selector": {
            "data": [
              {
                "scopeId": {
                  "Comparison": {
                    "ComparisonKind": 0,
                    "Left": {
                      "Column": {
                        "Expression": {
                          "SourceRef": {
                            "Entity": "CompanyMasters"
                          }
                        },
                        "Property": "Sub Company"
                      }
                    },
                    "Right": {
                      "Literal": {
                        "Value": "'MILNE ROAD SERVICES LLC'"
                      }
                    }
                  }
                }
              }
            ]
          }
        },
        {
          "properties": {
            "fill": {
              "solid": {
                "color": {
                  "expr": {
                    "Literal": {
                      "Value": "'#008B8B'"
                    }
                  }
                }
              }
            },
            "fillTransparency": {
              "expr": {
                "Literal": {
                  "Value": "0D"
                }
              }
            }
          },
          "selector": {
            "data": [
              {
                "scopeId": {
                  "Comparison": {
                    "ComparisonKind": 0,
                    "Left": {
                      "Column": {
                        "Expression": {
                          "SourceRef": {
                            "Entity": "CompanyMasters"
                          }
                        },
                        "Property": "Sub Company"
                      }
                    },
                    "Right": {
                      "Literal": {
                        "Value": "'ACTION ROAD SOLUTIONS, INC.'"
                      }
                    }
                  }
                }
              }
            ]
          }
        },
        {
          "properties": {
            "fill": {
              "solid": {
                "color": {
                  "expr": {
                    "Literal": {
                      "Value": "'#FF7F50'"
                    }
                  }
                }
              }
            }
          },
          "selector": {
            "data": [
              {
                "scopeId": {
                  "Comparison": {
                    "ComparisonKind": 0,
                    "Left": {
                      "Column": {
                        "Expression": {
                          "SourceRef": {
                            "Entity": "CompanyMasters"
                          }
                        },
                        "Property": "Sub Company"
                      }
                    },
                    "Right": {
                      "Literal": {
                        "Value": "'BIG VALLEY TOWING'"
                      }
                    }
                  }
                }
              }
            ]
          }
        },
        {
          "properties": {
            "fill": {
              "solid": {
                "color": {
                  "expr": {
                    "Literal": {
                      "Value": "'#40E0D0'"
                    }
                  }
                }
              }
            }
          },
          "selector": {
            "data": [
              {
                "scopeId": {
                  "Comparison": {
                    "ComparisonKind": 0,
                    "Left": {
                      "Column": {
                        "Expression": {
                          "SourceRef": {
                            "Entity": "CompanyMasters"
                          }
                        },
                        "Property": "Sub Company"
                      }
                    },
                    "Right": {
                      "Literal": {
                        "Value": "'CAL-NEVADA ROAD SERVICES LLC'"
                      }
                    }
                  }
                }
              }
            ]
          }
        },
        {
          "properties": {
            "fill": {
              "solid": {
                "color": {
                  "expr": {
                    "Literal": {
                      "Value": "'#D3D3D3'"
                    }
                  }
                }
              }
            }
          },
          "selector": {
            "data": [
              {
                "scopeId": {
                  "Comparison": {
                    "ComparisonKind": 0,
                    "Left": {
                      "Column": {
                        "Expression": {
                          "SourceRef": {
                            "Entity": "CompanyMasters"
                          }
                        },
                        "Property": "Sub Company"
                      }
                    },
                    "Right": {
                      "Literal": {
                        "Value": "'COLLEGE OAK ROAD SOLUTIONS LLC'"
                      }
                    }
                  }
                }
              }
            ]
          }
        },
        {
          "properties": {
            "fill": {
              "solid": {
                "color": {
                  "expr": {
                    "Literal": {
                      "Value": "'#A66999'"
                    }
                  }
                }
              }
            }
          },
          "selector": {
            "data": [
              {
                "scopeId": {
                  "Comparison": {
                    "ComparisonKind": 0,
                    "Left": {
                      "Column": {
                        "Expression": {
                          "SourceRef": {
                            "Entity": "CompanyMasters"
                          }
                        },
                        "Property": "Sub Company"
                      }
                    },
                    "Right": {
                      "Literal": {
                        "Value": "'ELLISONS TOWING'"
                      }
                    }
                  }
                }
              }
            ]
          }
        },
        {
          "properties": {
            "fill": {
              "solid": {
                "color": {
                  "expr": {
                    "ThemeDataColor": {
                      "ColorId": 7,
                      "Percent": 0
                    }
                  }
                }
              }
            }
          },
          "selector": {
            "data": [
              {
                "scopeId": {
                  "Comparison": {
                    "ComparisonKind": 0,
                    "Left": {
                      "Column": {
                        "Expression": {
                          "SourceRef": {
                            "Entity": "CompanyMasters"
                          }
                        },
                        "Property": "Sub Company"
                      }
                    },
                    "Right": {
                      "Literal": {
                        "Value": "'GREAT AMERICA TOWING'"
                      }
                    }
                  }
                }
              }
            ]
          }
        },
        {
          "properties": {
            "fill": {
              "solid": {
                "color": {
                  "expr": {
                    "Literal": {
                      "Value": "'#FFD1DC'"
                    }
                  }
                }
              }
            }
          },
          "selector": {
            "data": [
              {
                "scopeId": {
                  "Comparison": {
                    "ComparisonKind": 0,
                    "Left": {
                      "Column": {
                        "Expression": {
                          "SourceRef": {
                            "Entity": "CompanyMasters"
                          }
                        },
                        "Property": "Sub Company"
                      }
                    },
                    "Right": {
                      "Literal": {
                        "Value": "'CENTURY TOWING'"
                      }
                    }
                  }
                }
              }
            ]
          }
        }
      ]
    },
    "visualContainerObjects": {
      "visualTooltip": [
        {
          "properties": {
            "show": {
              "expr": {
                "Literal": {
                  "Value": "false"
                }
              }
            }
          }
        }
      ],
      "visualHeader": [
        {
          "properties": {
            "show": {
              "expr": {
                "Literal": {
                  "Value": "false"
                }
              }
            }
          }
        }
      ],
      "title": [
        {
          "properties": {
            "text": {
              "expr": {
                "Literal": {
                  "Value": "'Page Legend Chart'"
                }
              }
            },
            "fontSize": {
              "expr": {
                "Literal": {
                  "Value": "11D"
                }
              }
            },
            "fontFamily": {
              "expr": {
                "Literal": {
                  "Value": "'Calibri'"
                }
              }
            },
            "fontColor": {
              "solid": {
                "color": {
                  "expr": {
                    "ThemeDataColor": {
                      "ColorId": 0,
                      "Percent": -0.6
                    }
                  }
                }
              }
            },
            "show": {
              "expr": {
                "Literal": {
                  "Value": "false"
                }
              }
            }
          }
        }
      ],
      "background": [
        {
          "properties": {
            "show": {
              "expr": {
                "Literal": {
                  "Value": "false"
                }
              }
            }
          }
        }
      ]
    },
    "drillFilterOtherVisuals": true
  },
  "parentGroupName": "84a8494b70cd4a5685af"
}