{
  "$schema": "https://developer.microsoft.com/json-schemas/fabric/item/report/definition/visualContainer/2.7.0/schema.json",
  "name": "3eecc4b8130404283c6e",
  "position": {
    "x": 528.92857142857133,
    "y": 11.428571428571587,
    "z": 4000,
    "height": 40,
    "width": 165.83333333333334
  },
  "visual": {
    "visualType": "slicer",
    "query": {
      "queryState": {
        "Values": {
          "projections": [
            {
              "field": {
                "Column": {
                  "Expression": {
                    "SourceRef": {
                      "Entity": "agg agg_revenue_call_report_revenue"
                    }
                  },
                  "Property": "Duty Type"
                }
              },
              "queryRef": "agg agg_revenue_call_report_revenue.dutytype",
              "nativeQueryRef": "dutytype",
              "active": true
            },
            {
              "field": {
                "Column": {
                  "Expression": {
                    "SourceRef": {
                      "Entity": "agg agg_revenue_call_report_revenue"
                    }
                  },
                  "Property": "Truck Type"
                }
              },
              "queryRef": "agg agg_revenue_call_report_revenue.TruckType",
              "nativeQueryRef": "TruckType1",
              "active": false
            }
          ]
        }
      }
    },
    "objects": {
      "data": [
        {
          "properties": {
            "mode": {
              "expr": {
                "Literal": {
                  "Value": "'Dropdown'"
                }
              }
            }
          }
        }
      ],
      "header": [
        {
          "properties": {
            "show": {
              "expr": {
                "Literal": {
                  "Value": "false"
                }
              }
            }
          }
        }
      ],
      "items": [
        {
          "properties": {
            "fontFamily": {
              "expr": {
                "Literal": {
                  "Value": "'Calibri'"
                }
              }
            },
            "padding": {
              "expr": {
                "Literal": {
                  "Value": "4D"
                }
              }
            }
          }
        }
      ],
      "general": [
        {
          "properties": {}
        }
      ],
      "selection": [
        {
          "properties": {
            "singleSelect": {
              "expr": {
                "Literal": {
                  "Value": "false"
                }
              }
            },
            "selectAllCheckboxEnabled": {
              "expr": {
                "Literal": {
                  "Value": "true"
                }
              }
            }
          }
        }
      ]
    },
    "visualContainerObjects": {
      "background": [
        {
          "properties": {
            "show": {
              "expr": {
                "Literal": {
                  "Value": "false"
                }
              }
            }
          }
        }
      ],
      "visualHeader": [
        {
          "properties": {
            "show": {
              "expr": {
                "Literal": {
                  "Value": "false"
                }
              }
            }
          }
        }
      ],
      "title": [
        {
          "properties": {
            "text": {
              "expr": {
                "Literal": {
                  "Value": "'RTV_Slicer'"
                }
              }
            }
          }
        }
      ]
    },
    "syncGroup": {
      "groupName": "TruckType",
      "fieldChanges": true,
      "filterChanges": true
    },
    "drillFilterOtherVisuals": true
  },
  "parentGroupName": "6a008db71b277c167741",
  "filterConfig": {
    "filters": [
      {
        "name": "fb5cc4a0ec34607d4547",
        "field": {
          "Column": {
            "Expression": {
              "SourceRef": {
                "Entity": "agg agg_revenue_call_report_revenue"
              }
            },
            "Property": "Truck Type"
          }
        },
        "type": "Advanced",
        "filter": {
          "Version": 2,
          "From": [
            {
              "Name": "a1",
              "Entity": "agg agg_revenue_call_report_revenue",
              "Type": 0
            }
          ],
          "Where": [
            {
              "Condition": {
                "Not": {
                  "Expression": {
                    "Comparison": {
                      "ComparisonKind": 0,
                      "Left": {
                        "Column": {
                          "Expression": {
                            "SourceRef": {
                              "Source": "a1"
                            }
                          },
                          "Property": "Truck Type"
                        }
                      },
                      "Right": {
                        "Literal": {
                          "Value": "null"
                        }
                      }
                    }
                  }
                }
              }
            }
          ]
        }
      },
      {
        "name": "527f41e790db287483ac",
        "field": {
          "Column": {
            "Expression": {
              "SourceRef": {
                "Entity": "agg agg_revenue_call_report_revenue"
              }
            },
            "Property": "Duty Type"
          }
        },
        "type": "Advanced",
        "filter": {
          "Version": 2,
          "From": [
            {
              "Name": "a1",
              "Entity": "agg agg_revenue_call_report_revenue",
              "Type": 0
            }
          ],
          "Where": [
            {
              "Condition": {
                "Not": {
                  "Expression": {
                    "Comparison": {
                      "ComparisonKind": 0,
                      "Left": {
                        "Column": {
                          "Expression": {
                            "SourceRef": {
                              "Source": "a1"
                            }
                          },
                          "Property": "Duty Type"
                        }
                      },
                      "Right": {
                        "Literal": {
                          "Value": "null"
                        }
                      }
                    }
                  }
                }
              }
            }
          ]
        }
      }
    ]
  }
}